rolewalk.py
rolewalk-1.0.1.dist-info/LICENSE.txt
rolewalk-1.0.1.dist-info/METADATA
rolewalk-1.0.1.dist-info/WHEEL
rolewalk-1.0.1.dist-info/top_level.txt
rolewalk-1.0.1.dist-info/RECORD
